setup.py
feiwu/__init__.py
feiwu/cfgtools.py
feiwu/flask_helper.py
feiwu/flask_logging.py
feiwu/ipcool
feiwu/json_utils.py
feiwu/provinces.json
feiwu/readip.py
feiwu/utils.py
feiwu.egg-info/PKG-INFO
feiwu.egg-info/SOURCES.txt
feiwu.egg-info/dependency_links.txt
feiwu.egg-info/not-zip-safe
feiwu.egg-info/requires.txt
feiwu.egg-info/top_level.txt