Metadata-Version: 1.1
Name: feiwu
Version: 0.0.2
Summary: some useful module on flask developer
Home-page: UNKNOWN
Author: chen
Author-email: chenyehai737@qq.com
License: MIT
Keywords: web flask
Platform: UNKNOWN
Classifier: Programming Language :: Python :: 2.6
Classifier: Programming Language :: Python :: 2.7
